HISTORY.rst
LICENSE
MANIFEST.in
README.rst
requirements.txt
requirements_test.txt
setup.py
haul/__init__.py
haul/api.py
haul/compat.py
haul/core.py
haul/exceptions.py
haul/settings.py
haul/utils.py
haul.egg-info/PKG-INFO
haul.egg-info/SOURCES.txt
haul.egg-info/dependency_links.txt
haul.egg-info/not-zip-safe
haul.egg-info/requires.txt
haul.egg-info/top_level.txt
haul/extenders/__init__.py
haul/extenders/pipeline/__init__.py
haul/extenders/pipeline/google.py
haul/extenders/pipeline/pinterest.py
haul/extenders/pipeline/tumblr.py
haul/extenders/pipeline/wordpress.py
haul/finders/__init__.py
haul/finders/pipeline/__init__.py
haul/finders/pipeline/css.py
haul/finders/pipeline/html.py