Metadata-Version: 1.0
Name: haul
Version: 1.3.1
Summary: An Extensible Image Crawler
Home-page: https://github.com/vinta/Haul
Author: Vinta Chen
Author-email: vinta.chen@gmail.com
License: The MIT License (MIT)
